dashseo/__init__.py
dashseo/convert_to_html.py
dashseo-0.0.3.dist-info/METADATA
dashseo-0.0.3.dist-info/WHEEL
dashseo-0.0.3.dist-info/top_level.txt
dashseo-0.0.3.dist-info/RECORD
